utf_cleaner/__init__.py
utf_cleaner/cleaner.py
utf_cleaner/exceptions.py
utf_cleaner/logger.py
utf_cleaner/multiprocessing_handler.py
utf_cleaner/utils.py
utf_cleaner/validator.py
utf_cleaner-3.4.2.dist-info/LICENSE
utf_cleaner-3.4.2.dist-info/METADATA
utf_cleaner-3.4.2.dist-info/WHEEL
utf_cleaner-3.4.2.dist-info/top_level.txt
utf_cleaner-3.4.2.dist-info/RECORD
